[
  {
    "image": "https://images.pexels.com/photos/7720/night-animal-dog-pet.jpg?w=1260&h=750&auto=compress&cs=tinysrgb",
    "desc": "20",
    "image2": "https://images.pexels.com/photos/7720/night-animal-dog-pet.jpg?w=1260&h=750&auto=compress&cs=tinysrgb",
    "desc2": "20"
  },
  {
    "image": "https://images.pexels.com/photos/7720/night-animal-dog-pet.jpg?w=1260&h=750&auto=compress&cs=tinysrgb",
    "desc": "20",
    "image2": "https://images.pexels.com/photos/7720/night-animal-dog-pet.jpg?w=1260&h=750&auto=compress&cs=tinysrgb",
    "desc2": "20"
  }
]
